.coveragerc
.gitignore
CHANGELOG.rst
LICENSE.txt
README.rst
setup.py
setupext.py
.github/workflows/build.yml
lib/.gitignore
lib/dlsym.egg-info/PKG-INFO
lib/dlsym.egg-info/SOURCES.txt
lib/dlsym.egg-info/dependency_links.txt
lib/dlsym.egg-info/entry_points.txt
lib/dlsym.egg-info/top_level.txt
src/dlsym.cpp
tests/test_dlsym.py