Metadata-Version: 2.1
Name: dlsym
Version: 0.1
Summary: UNKNOWN
Home-page: https://github.com/anntzer/dlsym
Author: Antony Lee
Author-email: 
License: MIT
Platform: UNKNOWN
Classifier: Development Status :: 4 - Beta
Classifier: License :: OSI Approved :: zlib/libpng License
Classifier: Programming Language :: Python :: 3
Requires-Python: >=3.6
